{
  "formatVersion": 1,
  "nodes": [
    {
      "id": "0",
      "name": "Popup Frame",
      "children": [
        {
          "id": "22",
          "name": "Portrait",
          "children": [],
          "components": [
            {
              "type": "SpriteRenderer",
              "config": {
                "formatVersion": 1,
                "spriteAssetId": "153",
                "animationId": "0",
                "horizontalFlip": false,
                "verticalFlip": false,
                "castShadow": false,
                "receiveShadow": false,
                "color": "ffffff",
                "overrideOpacity": false,
                "opacity": null,
                "materialType": "basic",
                "shaderAssetId": null
              },
              "id": "0"
            }
          ],
          "position": {
            "x": -26,
            "y": 21,
            "z": 1
          },
          "orientation": {
            "x": 0,
            "y": 0,
            "z": 0,
            "w": 1
          },
          "scale": {
            "x": 1,
            "y": 1,
            "z": 1
          },
          "visible": true,
          "layer": 0,
          "prefab": null
        },
        {
          "id": "2",
          "name": "Title",
          "children": [],
          "components": [
            {
              "type": "TextRenderer",
              "config": {
                "formatVersion": 2,
                "fontAssetId": "133",
                "text": "Exhibition Offer",
                "alignment": "left",
                "verticalAlignment": "center",
                "size": null,
                "color": "b3f86d",
                "overrideOpacity": false,
                "opacity": null
              },
              "id": "1"
            }
          ],
          "position": {
            "x": -21,
            "y": 21,
            "z": 1
          },
          "orientation": {
            "x": 0,
            "y": 0,
            "z": 0,
            "w": 1
          },
          "scale": {
            "x": 1,
            "y": 1,
            "z": 1
          },
          "visible": true,
          "layer": 0,
          "prefab": null
        },
        {
          "id": "23",
          "name": "Details",
          "children": [],
          "components": [
            {
              "type": "TextRenderer",
              "config": {
                "formatVersion": 2,
                "fontAssetId": "9",
                "text": "Refuse at your own risk... and reputation.",
                "alignment": "left",
                "verticalAlignment": "center",
                "size": 48,
                "color": "b3f86d",
                "overrideOpacity": false,
                "opacity": null
              },
              "id": "1"
            }
          ],
          "position": {
            "x": -21,
            "y": 18.5,
            "z": 1
          },
          "orientation": {
            "x": 0,
            "y": 0,
            "z": 0,
            "w": 1
          },
          "scale": {
            "x": 1,
            "y": 1,
            "z": 1
          },
          "visible": true,
          "layer": 0,
          "prefab": null
        },
        {
          "id": "21",
          "name": "Offer Text",
          "children": [],
          "components": [
            {
              "type": "TextRenderer",
              "config": {
                "formatVersion": 2,
                "fontAssetId": "9",
                "text": "Text...",
                "alignment": "left",
                "verticalAlignment": "top",
                "size": null,
                "color": "00de6e",
                "overrideOpacity": false,
                "opacity": null
              },
              "id": "0"
            }
          ],
          "position": {
            "x": -29,
            "y": 14,
            "z": 1
          },
          "orientation": {
            "x": 0,
            "y": 0,
            "z": 0,
            "w": 1
          },
          "scale": {
            "x": 1,
            "y": 1,
            "z": 1
          },
          "visible": true,
          "layer": 0,
          "prefab": null
        },
        {
          "id": "24",
          "name": "Reward Label",
          "children": [],
          "components": [
            {
              "type": "TextRenderer",
              "config": {
                "formatVersion": 2,
                "fontAssetId": "9",
                "text": "Reward for participating:",
                "alignment": "left",
                "verticalAlignment": "center",
                "size": 48,
                "color": "aaaaaa",
                "overrideOpacity": false,
                "opacity": null
              },
              "id": "0"
            }
          ],
          "position": {
            "x": -29,
            "y": -10.25,
            "z": 1
          },
          "orientation": {
            "x": 0,
            "y": 0,
            "z": 0,
            "w": 1
          },
          "scale": {
            "x": 1,
            "y": 1,
            "z": 1
          },
          "visible": true,
          "layer": 0,
          "prefab": null
        },
        {
          "id": "25",
          "name": "Reward",
          "children": [],
          "components": [
            {
              "type": "TextRenderer",
              "config": {
                "formatVersion": 2,
                "fontAssetId": "9",
                "text": "$ 1234, 5 ⋆",
                "alignment": "left",
                "verticalAlignment": "center",
                "size": null,
                "color": null,
                "overrideOpacity": false,
                "opacity": null
              },
              "id": "0"
            }
          ],
          "position": {
            "x": -29,
            "y": -12.5,
            "z": 1
          },
          "orientation": {
            "x": 0,
            "y": 0,
            "z": 0,
            "w": 1
          },
          "scale": {
            "x": 1,
            "y": 1,
            "z": 1
          },
          "visible": true,
          "layer": 0,
          "prefab": null
        },
        {
          "id": "10",
          "name": "Accept Button",
          "children": [
            {
              "id": "11",
              "name": "Text",
              "children": [],
              "components": [
                {
                  "type": "TextRenderer",
                  "config": {
                    "formatVersion": 2,
                    "fontAssetId": "133",
                    "text": "ACCEPT",
                    "alignment": "center",
                    "verticalAlignment": "center",
                    "size": null,
                    "color": null,
                    "overrideOpacity": false,
                    "opacity": null
                  },
                  "id": "0"
                }
              ],
              "position": {
                "x": 0,
                "y": 0,
                "z": 0
              },
              "orientation": {
                "x": 0,
                "y": 0,
                "z": 0,
                "w": 1
              },
              "scale": {
                "x": 1,
                "y": 1,
                "z": 1
              },
              "visible": true,
              "layer": 0,
              "prefab": null
            }
          ],
          "components": [
            {
              "type": "SpriteRenderer",
              "config": {
                "formatVersion": 1,
                "spriteAssetId": "28",
                "animationId": null,
                "horizontalFlip": false,
                "verticalFlip": false,
                "castShadow": false,
                "receiveShadow": false,
                "color": "ffffff",
                "overrideOpacity": false,
                "opacity": null,
                "materialType": "basic",
                "shaderAssetId": null
              },
              "id": "0"
            },
            {
              "type": "Behavior",
              "config": {
                "behaviorName": "ButtonBehavior",
                "propertyValues": {}
              },
              "id": "1"
            }
          ],
          "position": {
            "x": 23,
            "y": -12,
            "z": 1
          },
          "orientation": {
            "x": 0,
            "y": 0,
            "z": 0,
            "w": 1
          },
          "scale": {
            "x": 1,
            "y": 1,
            "z": 1
          },
          "visible": true,
          "layer": 0,
          "prefab": null
        },
        {
          "id": "19",
          "name": "Decline Button",
          "children": [
            {
              "id": "20",
              "name": "Text",
              "children": [],
              "components": [
                {
                  "type": "TextRenderer",
                  "config": {
                    "formatVersion": 2,
                    "fontAssetId": "133",
                    "text": "DECLINE",
                    "alignment": "center",
                    "verticalAlignment": "center",
                    "size": null,
                    "color": null,
                    "overrideOpacity": false,
                    "opacity": null
                  },
                  "id": "0"
                }
              ],
              "position": {
                "x": 0,
                "y": 0,
                "z": 0
              },
              "orientation": {
                "x": 0,
                "y": 0,
                "z": 0,
                "w": 1
              },
              "scale": {
                "x": 1,
                "y": 1,
                "z": 1
              },
              "visible": true,
              "layer": 0,
              "prefab": null
            }
          ],
          "components": [
            {
              "type": "SpriteRenderer",
              "config": {
                "formatVersion": 1,
                "spriteAssetId": "84",
                "animationId": null,
                "horizontalFlip": false,
                "verticalFlip": false,
                "castShadow": false,
                "receiveShadow": false,
                "color": "ffffff",
                "overrideOpacity": false,
                "opacity": null,
                "materialType": "basic",
                "shaderAssetId": null
              },
              "id": "0"
            },
            {
              "type": "Behavior",
              "config": {
                "behaviorName": "ButtonBehavior",
                "propertyValues": {}
              },
              "id": "1"
            }
          ],
          "position": {
            "x": 9,
            "y": -12,
            "z": 1
          },
          "orientation": {
            "x": 0,
            "y": 0,
            "z": 0,
            "w": 1
          },
          "scale": {
            "x": 1,
            "y": 1,
            "z": 1
          },
          "visible": true,
          "layer": 0,
          "prefab": null
        }
      ],
      "components": [
        {
          "type": "SpriteRenderer",
          "config": {
            "formatVersion": 1,
            "spriteAssetId": "56",
            "animationId": null,
            "horizontalFlip": false,
            "verticalFlip": false,
            "castShadow": false,
            "receiveShadow": false,
            "color": "ffffff",
            "overrideOpacity": false,
            "opacity": null,
            "materialType": "basic",
            "shaderAssetId": null
          },
          "id": "0"
        },
        {
          "type": "Behavior",
          "config": {
            "behaviorName": "ExhibitionPopupBehavior",
            "propertyValues": {}
          },
          "id": "1"
        }
      ],
      "position": {
        "x": 0,
        "y": -4,
        "z": 0
      },
      "orientation": {
        "x": 0,
        "y": 0,
        "z": 0,
        "w": 1
      },
      "scale": {
        "x": 1,
        "y": 1,
        "z": 1
      },
      "visible": true,
      "layer": 0,
      "prefab": null
    }
  ]
}